setup.py
odoo/addons/helpdesk_stage_transition/CHANGELOG.md
odoo/addons/helpdesk_stage_transition/README.rst
odoo/addons/helpdesk_stage_transition/__init__.py
odoo/addons/helpdesk_stage_transition/__manifest__.py
odoo/addons/helpdesk_stage_transition/i18n/es.mo
odoo/addons/helpdesk_stage_transition/i18n/es.po
odoo/addons/helpdesk_stage_transition/i18n/helpdesk_stage_transition.pot
odoo/addons/helpdesk_stage_transition/models/__init__.py
odoo/addons/helpdesk_stage_transition/models/helpdesk_ticket.py
odoo/addons/helpdesk_stage_transition/models/helpdesk_ticket_stage.py
odoo/addons/helpdesk_stage_transition/security/ir.model.access.csv
odoo/addons/helpdesk_stage_transition/static/description/icon.png
odoo/addons/helpdesk_stage_transition/views/helpdesk_ticket_stage_views.xml
odoo/addons/helpdesk_stage_transition/views/helpdesk_ticket_views.xml
odoo_addon_helpdesk_stage_transition.egg-info/PKG-INFO
odoo_addon_helpdesk_stage_transition.egg-info/SOURCES.txt
odoo_addon_helpdesk_stage_transition.egg-info/dependency_links.txt
odoo_addon_helpdesk_stage_transition.egg-info/not-zip-safe
odoo_addon_helpdesk_stage_transition.egg-info/requires.txt
odoo_addon_helpdesk_stage_transition.egg-info/top_level.txt