Metadata-Version: 2.1
Name: odoo-addon-helpdesk-stage-transition
Version: 16.0.1.0.2
Summary: Allows to define transitions between helpdesk ticket stages and adds buttons to the helpdesk ticket form to trigger them. This module also disables drag and drop in the kanban view.
Home-page: https://somit.coop
Author: Som IT Cooperatiu SCCL
License: AGPL-3
Classifier: Programming Language :: Python
Classifier: Framework :: Odoo
Classifier: Framework :: Odoo :: 16.0
Classifier: License :: OSI Approved :: GNU Affero General Public License v3
Requires-Python: >=3.10
